gerby/__init__.py
gerby/clients/__init__.py
gerby/clients/forecast_client.py
gerby/clients/glass_frog_client.py
gerby/clients/guru_client.py
gerby/clients/harvest_client.py
gerby/clients/pivotal_tracker_client.py
gerby/clients/slack_client.py
gerby/constants.py
gerby/data/__init__.py
gerby/data/assignments.py
gerby/data/entries.py
gerby/data/helpers.py
gerby/data/projects.py
gerby/data/users.py
gerby/secrets.py
gerby-0.3.0.dist-info/WHEEL
gerby-0.3.0.dist-info/METADATA
gerby-0.3.0.dist-info/RECORD
